Metadata-Version: 2.1
Name: rasa-middleware-connector
Version: 0.2.1
Summary: Adds middleware support for rasa connectors
Home-page: https://github.com/guilherme1guy/rasa_middleware_connector
Author: Guilherme Guy
Author-email: guilhermeguy349@gmail.com
License: MIT
Keywords: rasa,rasa core,rasa channels
Platform: UNKNOWN
Classifier: Development Status :: 3 - Alpha
Classifier: Intended Audience :: Developers
Classifier: Topic :: Software Development :: Build Tools
Classifier: License :: OSI Approved :: MIT License
Classifier: Programming Language :: Python :: 3.5
Classifier: Programming Language :: Python :: 3.6
Classifier: Programming Language :: Python :: 3.7
